firebolt_db/__init__.py
firebolt_db/firebolt_async_dialect.py
firebolt_db/firebolt_dialect.py
firebolt_sqlalchemy-1.1.1.dist-info/LICENSE
firebolt_sqlalchemy-1.1.1.dist-info/METADATA
firebolt_sqlalchemy-1.1.1.dist-info/WHEEL
firebolt_sqlalchemy-1.1.1.dist-info/entry_points.txt
firebolt_sqlalchemy-1.1.1.dist-info/top_level.txt
firebolt_sqlalchemy-1.1.1.dist-info/RECORD
