Metadata-Version: 2.1
Name: firebolt_sqlalchemy
Version: 1.1.1
Summary: Sqlalchemy adapter for Firebolt
Home-page: https://github.com/firebolt-db/firebolt-sqlalchemy
Download-URL: https://github.com/firebolt-db/firebolt-sqlalchemy/archive/refs/tags/0.0.9.tar.gz
Author: Firebolt
Author-email: pypi@firebolt.io
License: Apache-2.0
Project-URL: Bug Tracker, https://github.com/firebolt-db/firebolt-sqlalchemy
Classifier: License :: OSI Approved :: Apache Software License
Classifier: License :: OSI Approved :: MIT License
Classifier: Operating System :: OS Independent
Classifier: Programming Language :: Python :: 3
Classifier: Programming Language :: Python :: 3 :: Only
Classifier: Programming Language :: Python :: 3.9
Classifier: Programming Language :: Python :: 3.10
Classifier: Programming Language :: Python :: 3.11
Classifier: Programming Language :: Python :: 3.12
Requires-Python: >=3.9
License-File: LICENSE
Requires-Dist: firebolt-sdk>=1.13.0
Requires-Dist: sqlalchemy>=1.0.0
Provides-Extra: dev
Requires-Dist: allure-pytest==2.*; extra == "dev"
Requires-Dist: devtools==0.7.0; extra == "dev"
Requires-Dist: greenlet==3.2.4; extra == "dev"
Requires-Dist: mock==4.0.3; extra == "dev"
Requires-Dist: mypy==0.910; extra == "dev"
Requires-Dist: pre-commit==3.5.0; extra == "dev"
Requires-Dist: pytest==7.2.0; extra == "dev"
Requires-Dist: pytest-cov==3.0.0; extra == "dev"
Requires-Dist: pytest-trio==0.8.0; extra == "dev"
Requires-Dist: sqlalchemy-stubs==0.4; extra == "dev"
Requires-Dist: trio-typing==0.9.0; extra == "dev"
